visitors/__init__.py
visitors/admin.py
visitors/apps.py
visitors/context_processors.py
visitors/decorators.py
visitors/middleware.py
visitors/migrations/0001_initial.py
visitors/migrations/0002_visitorlog.py
visitors/migrations/__init__.py
visitors/models.py
visitors/settings.py
django_visitors-0.1.1.dist-info/LICENSE
django_visitors-0.1.1.dist-info/WHEEL
django_visitors-0.1.1.dist-info/METADATA
django_visitors-0.1.1.dist-info/RECORD
