Metadata-Version: 2.1
Name: django-visitors
Version: 0.1.1
Summary: Django support for 'visitors' - who are neither anonymous nor authenticated.
Home-page: https://github.com/yunojuno/django-visitors
License: MIT
Author: YunoJuno
Author-email: code@yunojuno.com
Maintainer: YunoJuno
Maintainer-email: code@yunojuno.com
Requires-Python: >=3.7,<4.0
Classifier: Development Status :: 4 - Beta
Classifier: Environment :: Web Environment
Classifier: Framework :: Django
Classifier: Framework :: Django :: 3.1
Classifier: License :: OSI Approved :: MIT License
Classifier: Operating System :: OS Independent
Classifier: Programming Language :: Python :: 3
Classifier: Programming Language :: Python :: 3 :: Only
Classifier: Programming Language :: Python :: 3.7
Classifier: Programming Language :: Python :: 3.8
Classifier: Programming Language :: Python :: 3.9
Requires-Dist: django (>=3.0,<4.0)
Project-URL: Documentation, https://github.com/yunojuno/django-visitors
Project-URL: Repository, https://github.com/yunojuno/django-visitors
